future_sales_prediction_2024/__init__.py
future_sales_prediction_2024/data_handling.py
future_sales_prediction_2024/data_loader.py
future_sales_prediction_2024/model_analysis.py
future_sales_prediction_2024/model_training.py
future_sales_prediction_2024/validation.py
future_sales_prediction_2024-3.4.17.dist-info/LICENSE
future_sales_prediction_2024-3.4.17.dist-info/METADATA
future_sales_prediction_2024-3.4.17.dist-info/WHEEL
future_sales_prediction_2024-3.4.17.dist-info/top_level.txt
future_sales_prediction_2024-3.4.17.dist-info/RECORD
