Metadata-Version: 2.1
Name: future_sales_prediction_2024
Version: 3.4.17
Summary: A package for feature extraction, hyperopt, and validation schemas
Author: Polina Yatsko
Author-email: yatsko_polina1@mail.ru
License: MIT
Keywords: machine-learning xgboost hyperopt data-science regression
Classifier: Programming Language :: Python :: 3.12
Classifier: Topic :: Scientific/Engineering :: Information Analysis
Classifier: Operating System :: OS Independent
Requires-Python: >=3.7,<3.13
License-File: LICENSE
Requires-Dist: pandas
Requires-Dist: numpy
Requires-Dist: scikit-learn
Requires-Dist: lightgbm
Requires-Dist: xgboost
Requires-Dist: matplotlib
Requires-Dist: seaborn
Requires-Dist: hyperopt
Requires-Dist: shap
Requires-Dist: matplotlib
Requires-Dist: seaborn
